pyqt_screen_capture.py
pyqt_screen_capture-0.1.1.dist-info/licenses/LICENSE
pyqt_screen_capture-0.1.1.dist-info/METADATA
pyqt_screen_capture-0.1.1.dist-info/WHEEL
pyqt_screen_capture-0.1.1.dist-info/top_level.txt
pyqt_screen_capture-0.1.1.dist-info/RECORD
