Metadata-Version: 2.4
Name: pyqt-screen-capture
Version: 0.1.1
Summary: A screen capture utility that works with PyQt6, PySide6, PyQt5, PySide2, and PySide.
Author-email: Jifeng Wu <jifengwu2k@gmail.com>
License-Expression: MIT
Project-URL: Homepage, https://github.com/jifengwu2k/pyqt-screen-capture
Project-URL: Bug Tracker, https://github.com/jifengwu2k/pyqt-screen-capture/issues
Classifier: Programming Language :: Python :: 2
Classifier: Programming Language :: Python :: 3
Classifier: Operating System :: OS Independent
Requires-Python: >=2
License-File: LICENSE
Requires-Dist: numpy
Provides-Extra: pyqt6
Requires-Dist: PyQt6; extra == "pyqt6"
Provides-Extra: pyside6
Requires-Dist: PySide6; extra == "pyside6"
Provides-Extra: pyqt5
Requires-Dist: PyQt5; extra == "pyqt5"
Provides-Extra: pyside2
Requires-Dist: PySide2; extra == "pyside2"
Provides-Extra: pyside
Requires-Dist: PySide; extra == "pyside"
Dynamic: license-file
